MANIFEST.in
README.md
setup.py
sm2py/__init__.py
sm2py/curv.c
sm2py/functions.py
sm2py/sm2.py
sm2py.egg-info/PKG-INFO
sm2py.egg-info/SOURCES.txt
sm2py.egg-info/dependency_links.txt
sm2py.egg-info/requires.txt
sm2py.egg-info/top_level.txt
sm2py.egg-info/zip-safe
tests/__init__.py
tests/test.py