Metadata-Version: 2.1
Name: sm2py
Version: 0.1.0
Summary: Python version SM2 keypair generator signature and verify, ecdh secret sharing, for human mind
Home-page: https://github.com/ipconfiger/sm2py
Author: Alexander.Li
Author-email: superpowerlee@gmail.com
License: GPLv2+
Keywords: ecc,ecdh,secp256k1,signature,verification
Platform: UNKNOWN
